{
  "actionItems": [
    {
      "id": "memorial-scarf-2026",
      "itemCode": "game:clothes-shoulder-artisans-scarf",
      "name": "<font color=\"#8B5CF6\">Памятный шарф 2026</font>",
      "description": "<font color=\"#60A5FA\">Шарф с вышивкой, которую не хочется показывать. Тёплый, как обещание, которое никто не сдержал.\n</font>",
      "actions": [],
      "attributes": {
        "warmth": 2.0,
        "protection": 200.0,
        "attackpower": 200.0
      },
      "showAttributes": [
        "protection"
      ],
      "hideVanillaTooltips": [
        "attackpower"
      ]
    }
  ]
}